translation_module/__init__.py
translation_module/translator.py
translation_module-1.0.dist-info/License.txt
translation_module-1.0.dist-info/METADATA
translation_module-1.0.dist-info/WHEEL
translation_module-1.0.dist-info/top_level.txt
translation_module-1.0.dist-info/RECORD
