Metadata-Version: 2.1
Name: translation-module
Version: 1.0
Summary: A short description of your package
Home-page: https://github.com/your_username/your_package_name
Author: Falah.G.Salieh
Author-email: your_email@example.com
Classifier: License :: OSI Approved :: MIT License
Classifier: Programming Language :: Python :: 3
Classifier: Programming Language :: Python :: 3.6
Classifier: Programming Language :: Python :: 3.7
Classifier: Programming Language :: Python :: 3.8
License-File: License.txt
Requires-Dist: openai
Requires-Dist: diffusers
Requires-Dist: torch
Requires-Dist: safetensors
Requires-Dist: Pillow
